{
    "R_eff": 1.135126334322865,
    "u_R_eff": 0.34361997311284953,
    "today": "2021-09-20",
    "projection": [
        {
            "date": "2021-09-19",
            "cases": 20.0,
            "upper": 35.08452611351757,
            "lower": 4.9154738864824346
        },
        {
            "date": "2021-09-20",
            "cases": 20.0,
            "upper": 38.855657641896954,
            "lower": 4.9154738864824346
        },
        {
            "date": "2021-09-21",
            "cases": 21.0,
            "upper": 43.626789170276346,
            "lower": 2.1443423581030423
        },
        {
            "date": "2021-09-22",
            "cases": 21.0,
            "upper": 47.39792069865574,
            "lower": 2.1443423581030423
        },
        {
            "date": "2021-09-23",
            "cases": 21.0,
            "upper": 53.05461799122482,
            "lower": 0.2587765939133462
        },
        {
            "date": "2021-09-24",
            "cases": 22.0,
            "upper": 57.825749519604216,
            "lower": 0
        },
        {
            "date": "2021-09-25",
            "cases": 22.0,
            "upper": 63.48244681217331,
            "lower": 0
        },
        {
            "date": "2021-09-26",
            "cases": 22.0,
            "upper": 69.1391441047424,
            "lower": 0
        },
        {
            "date": "2021-09-27",
            "cases": 22.0,
            "upper": 74.79584139731148,
            "lower": 0
        },
        {
            "date": "2021-09-28",
            "cases": 22.0,
            "upper": 82.33810445407026,
            "lower": 0
        },
        {
            "date": "2021-09-29",
            "cases": 22.0,
            "upper": 86.10923598244965,
            "lower": 0
        },
        {
            "date": "2021-09-30",
            "cases": 22.0,
            "upper": 93.65149903920843,
            "lower": 0
        },
        {
            "date": "2021-10-01",
            "cases": 22.0,
            "upper": 101.19376209596722,
            "lower": 0
        },
        {
            "date": "2021-10-02",
            "cases": 22.0,
            "upper": 106.85045938853631,
            "lower": 0
        },
        {
            "date": "2021-10-03",
            "cases": 22.0,
            "upper": 114.39272244529509,
            "lower": 0
        },
        {
            "date": "2021-10-04",
            "cases": 22.0,
            "upper": 121.93498550205388,
            "lower": 0
        },
        {
            "date": "2021-10-05",
            "cases": 22.0,
            "upper": 129.47724855881265,
            "lower": 0
        },
        {
            "date": "2021-10-06",
            "cases": 22.0,
            "upper": 135.13394585138172,
            "lower": 0
        },
        {
            "date": "2021-10-07",
            "cases": 21.0,
            "upper": 141.67620890814052,
            "lower": 0
        },
        {
            "date": "2021-10-08",
            "cases": 21.0,
            "upper": 149.2184719648993,
            "lower": 0
        },
        {
            "date": "2021-10-09",
            "cases": 20.0,
            "upper": 157.64630078584779,
            "lower": 0
        },
        {
            "date": "2021-10-10",
            "cases": 20.0,
            "upper": 161.41743231422717,
            "lower": 0
        },
        {
            "date": "2021-10-11",
            "cases": 19.0,
            "upper": 167.95969537098597,
            "lower": 0
        },
        {
            "date": "2021-10-12",
            "cases": 19.0,
            "upper": 171.73082689936535,
            "lower": 0
        },
        {
            "date": "2021-10-13",
            "cases": 18.0,
            "upper": 176.38752419193443,
            "lower": 0
        },
        {
            "date": "2021-10-14",
            "cases": 18.0,
            "upper": 180.15865572031382,
            "lower": 0
        },
        {
            "date": "2021-10-15",
            "cases": 17.0,
            "upper": 184.81535301288292,
            "lower": 0
        },
        {
            "date": "2021-10-16",
            "cases": 17.0,
            "upper": 188.5864845412623,
            "lower": 0
        },
        {
            "date": "2021-10-17",
            "cases": 16.0,
            "upper": 195.12874759802108,
            "lower": 0
        },
        {
            "date": "2021-10-18",
            "cases": 15.0,
            "upper": 190.3576160696417,
            "lower": 0
        },
        {
            "date": "2021-10-19",
            "cases": 14.0,
            "upper": 196.8998791264005,
            "lower": 0
        },
        {
            "date": "2021-10-20",
            "cases": 14.0,
            "upper": 196.8998791264005,
            "lower": 0
        },
        {
            "date": "2021-10-21",
            "cases": 13.0,
            "upper": 197.78544489059018,
            "lower": 0
        },
        {
            "date": "2021-10-22",
            "cases": 12.0,
            "upper": 193.01431336221077,
            "lower": 0
        },
        {
            "date": "2021-10-23",
            "cases": 11.0,
            "upper": 193.8998791264005,
            "lower": 0
        },
        {
            "date": "2021-10-24",
            "cases": 11.0,
            "upper": 192.01431336221077,
            "lower": 0
        },
        {
            "date": "2021-10-25",
            "cases": 10.0,
            "upper": 189.12874759802108,
            "lower": 0
        },
        {
            "date": "2021-10-26",
            "cases": 10.0,
            "upper": 185.3576160696417,
            "lower": 0
        },
        {
            "date": "2021-10-27",
            "cases": 9.0,
            "upper": 182.472050305452,
            "lower": 0
        },
        {
            "date": "2021-10-28",
            "cases": 8.0,
            "upper": 177.70091877707262,
            "lower": 0
        },
        {
            "date": "2021-10-29",
            "cases": 7.0,
            "upper": 172.92978724869323,
            "lower": 0
        },
        {
            "date": "2021-10-30",
            "cases": 7.0,
            "upper": 169.15865572031382,
            "lower": 0
        },
        {
            "date": "2021-10-31",
            "cases": 6.0,
            "upper": 162.50195842774474,
            "lower": 0
        },
        {
            "date": "2021-11-01",
            "cases": 6.0,
            "upper": 154.95969537098597,
            "lower": 0
        },
        {
            "date": "2021-11-02",
            "cases": 5.0,
            "upper": 150.18856384260656,
            "lower": 0
        },
        {
            "date": "2021-11-03",
            "cases": 5.0,
            "upper": 144.53186655003748,
            "lower": 0
        },
        {
            "date": "2021-11-04",
            "cases": 5.0,
            "upper": 135.10403772908901,
            "lower": 0
        },
        {
            "date": "2021-11-05",
            "cases": 4.0,
            "upper": 128.4473404365199,
            "lower": 0
        },
        {
            "date": "2021-11-06",
            "cases": 4.0,
            "upper": 122.79064314395083,
            "lower": 0
        },
        {
            "date": "2021-11-07",
            "cases": 3.0,
            "upper": 116.13394585138174,
            "lower": 0
        },
        {
            "date": "2021-11-08",
            "cases": 3.0,
            "upper": 108.59168279462295,
            "lower": 0
        },
        {
            "date": "2021-11-09",
            "cases": 3.0,
            "upper": 101.04941973786417,
            "lower": 0
        },
        {
            "date": "2021-11-10",
            "cases": 2.0,
            "upper": 94.39272244529509,
            "lower": 0
        },
        {
            "date": "2021-11-11",
            "cases": 2.0,
            "upper": 88.736025152726,
            "lower": 0
        },
        {
            "date": "2021-11-12",
            "cases": 2.0,
            "upper": 83.07932786015691,
            "lower": 0
        },
        {
            "date": "2021-11-13",
            "cases": 2.0,
            "upper": 77.42263056758783,
            "lower": 0
        },
        {
            "date": "2021-11-14",
            "cases": 2.0,
            "upper": 71.76593327501874,
            "lower": 0
        },
        {
            "date": "2021-11-15",
            "cases": 1.0,
            "upper": 68.88036751082905,
            "lower": 0
        },
        {
            "date": "2021-11-16",
            "cases": 1.0,
            "upper": 65.10923598244965,
            "lower": 0
        },
        {
            "date": "2021-11-17",
            "cases": 1.0,
            "upper": 61.33810445407026,
            "lower": 0
        },
        {
            "date": "2021-11-18",
            "cases": 1.0,
            "upper": 57.56697292569087,
            "lower": 0
        },
        {
            "date": "2021-11-19",
            "cases": 1.0,
            "upper": 53.79584139731148,
            "lower": 0
        },
        {
            "date": "2021-11-20",
            "cases": 1.0,
            "upper": 50.024709868932085,
            "lower": 0
        },
        {
            "date": "2021-11-21",
            "cases": 1.0,
            "upper": 46.25357834055269,
            "lower": 0
        },
        {
            "date": "2021-11-22",
            "cases": 1.0,
            "upper": 44.368012576363,
            "lower": 0
        },
        {
            "date": "2021-11-23",
            "cases": 0.0,
            "upper": 41.48244681217331,
            "lower": 0.0
        },
        {
            "date": "2021-11-24",
            "cases": 0.0,
            "upper": 39.59688104798361,
            "lower": 0.0
        },
        {
            "date": "2021-11-25",
            "cases": 0.0,
            "upper": 37.711315283793915,
            "lower": 0.0
        },
        {
            "date": "2021-11-26",
            "cases": 0.0,
            "upper": 35.825749519604216,
            "lower": 0.0
        },
        {
            "date": "2021-11-27",
            "cases": 0.0,
            "upper": 33.94018375541452,
            "lower": 0.0
        },
        {
            "date": "2021-11-28",
            "cases": 0.0,
            "upper": 32.05461799122482,
            "lower": 0.0
        },
        {
            "date": "2021-11-29",
            "cases": 0.0,
            "upper": 30.16905222703513,
            "lower": 0.0
        },
        {
            "date": "2021-11-30",
            "cases": 0.0,
            "upper": 28.283486462845435,
            "lower": 0.0
        },
        {
            "date": "2021-12-01",
            "cases": 0.0,
            "upper": 26.39792069865574,
            "lower": 0.0
        },
        {
            "date": "2021-12-02",
            "cases": 0.0,
            "upper": 24.512354934466043,
            "lower": 0.0
        },
        {
            "date": "2021-12-03",
            "cases": 0.0,
            "upper": 22.626789170276346,
            "lower": 0.0
        },
        {
            "date": "2021-12-04",
            "cases": 0.0,
            "upper": 22.626789170276346,
            "lower": 0.0
        },
        {
            "date": "2021-12-05",
            "cases": 0.0,
            "upper": 20.741223406086654,
            "lower": 0.0
        },
        {
            "date": "2021-12-06",
            "cases": 0.0,
            "upper": 18.855657641896958,
            "lower": 0.0
        },
        {
            "date": "2021-12-07",
            "cases": 0.0,
            "upper": 18.855657641896958,
            "lower": 0.0
        },
        {
            "date": "2021-12-08",
            "cases": 0.0,
            "upper": 16.97009187770726,
            "lower": 0.0
        },
        {
            "date": "2021-12-09",
            "cases": 0.0,
            "upper": 16.97009187770726,
            "lower": 0.0
        },
        {
            "date": "2021-12-10",
            "cases": 0.0,
            "upper": 15.084526113517565,
            "lower": 0.0
        },
        {
            "date": "2021-12-11",
            "cases": 0.0,
            "upper": 15.084526113517565,
            "lower": 0.0
        },
        {
            "date": "2021-12-12",
            "cases": 0.0,
            "upper": 13.19896034932787,
            "lower": 0.0
        },
        {
            "date": "2021-12-13",
            "cases": 0.0,
            "upper": 13.19896034932787,
            "lower": 0.0
        },
        {
            "date": "2021-12-14",
            "cases": 0.0,
            "upper": 11.313394585138173,
            "lower": 0.0
        },
        {
            "date": "2021-12-15",
            "cases": 0.0,
            "upper": 11.313394585138173,
            "lower": 0.0
        },
        {
            "date": "2021-12-16",
            "cases": 0.0,
            "upper": 11.313394585138173,
            "lower": 0.0
        },
        {
            "date": "2021-12-17",
            "cases": 0.0,
            "upper": 9.427828820948479,
            "lower": 0.0
        },
        {
            "date": "2021-12-18",
            "cases": 0.0,
            "upper": 9.427828820948479,
            "lower": 0.0
        },
        {
            "date": "2021-12-19",
            "cases": 0.0,
            "upper": 9.427828820948479,
            "lower": 0.0
        },
        {
            "date": "2021-12-20",
            "cases": 0.0,
            "upper": 9.427828820948479,
            "lower": 0.0
        },
        {
            "date": "2021-12-21",
            "cases": 0.0,
            "upper": 7.542263056758783,
            "lower": 0.0
        },
        {
            "date": "2021-12-22",
            "cases": 0.0,
            "upper": 7.542263056758783,
            "lower": 0.0
        },
        {
            "date": "2021-12-23",
            "cases": 0.0,
            "upper": 7.542263056758783,
            "lower": 0.0
        },
        {
            "date": "2021-12-24",
            "cases": 0.0,
            "upper": 5.656697292569087,
            "lower": 0.0
        },
        {
            "date": "2021-12-25",
            "cases": 0.0,
            "upper": 5.656697292569087,
            "lower": 0.0
        },
        {
            "date": "2021-12-26",
            "cases": 0.0,
            "upper": 5.656697292569087,
            "lower": 0.0
        },
        {
            "date": "2021-12-27",
            "cases": 0.0,
            "upper": 5.656697292569087,
            "lower": 0.0
        },
        {
            "date": "2021-12-28",
            "cases": 0.0,
            "upper": 5.656697292569087,
            "lower": 0.0
        },
        {
            "date": "2021-12-29",
            "cases": 0.0,
            "upper": 5.656697292569087,
            "lower": 0.0
        },
        {
            "date": "2021-12-30",
            "cases": 0.0,
            "upper": 3.7711315283793914,
            "lower": 0.0
        },
        {
            "date": "2021-12-31",
            "cases": 0.0,
            "upper": 3.7711315283793914,
            "lower": 0.0
        },
        {
            "date": "2022-01-01",
            "cases": 0.0,
            "upper": 3.7711315283793914,
            "lower": 0.0
        },
        {
            "date": "2022-01-02",
            "cases": 0.0,
            "upper": 3.7711315283793914,
            "lower": 0.0
        },
        {
            "date": "2022-01-03",
            "cases": 0.0,
            "upper": 3.7711315283793914,
            "lower": 0.0
        },
        {
            "date": "2022-01-04",
            "cases": 0.0,
            "upper": 3.7711315283793914,
            "lower": 0.0
        },
        {
            "date": "2022-01-05",
            "cases": 0.0,
            "upper": 3.7711315283793914,
            "lower": 0.0
        },
        {
            "date": "2022-01-06",
            "cases": 0.0,
            "upper": 1.8855657641896957,
            "lower": 0.0
        },
        {
            "date": "2022-01-07",
            "cases": 0.0,
            "upper": 1.8855657641896957,
            "lower": 0.0
        },
        {
            "date": "2022-01-08",
            "cases": 0.0,
            "upper": 1.8855657641896957,
            "lower": 0.0
        },
        {
            "date": "2022-01-09",
            "cases": 0.0,
            "upper": 1.8855657641896957,
            "lower": 0.0
        },
        {
            "date": "2022-01-10",
            "cases": 0.0,
            "upper": 1.8855657641896957,
            "lower": 0.0
        },
        {
            "date": "2022-01-11",
            "cases": 0.0,
            "upper": 1.8855657641896957,
            "lower": 0.0
        },
        {
            "date": "2022-01-12",
            "cases": 0.0,
            "upper": 1.8855657641896957,
            "lower": 0.0
        },
        {
            "date": "2022-01-13",
            "cases": 0.0,
            "upper": 1.8855657641896957,
            "lower": 0.0
        },
        {
            "date": "2022-01-14",
            "cases": 0.0,
            "upper": 1.8855657641896957,
            "lower": 0.0
        },
        {
            "date": "2022-01-15",
            "cases": 0.0,
            "upper": 1.8855657641896957,
            "lower": 0.0
        },
        {
            "date": "2022-01-16",
            "cases": 0.0,
            "upper": 1.8855657641896957,
            "lower": 0.0
        },
        {
            "date": "2022-01-17",
            "cases": 0.0,
            "upper": 1.8855657641896957,
            "lower": 0.0
        },
        {
            "date": "2022-01-18",
            "cases": 0.0,
            "upper": 1.8855657641896957,
            "lower": 0.0
        },
        {
            "date": "2022-01-19",
            "cases": 0.0,
            "upper": 0.0,
            "lower": 0.0
        },
        {
            "date": "2022-01-20",
            "cases": 0.0,
            "upper": 0.0,
            "lower": 0.0
        },
        {
            "date": "2022-01-21",
            "cases": 0.0,
            "upper": 0.0,
            "lower": 0.0
        },
        {
            "date": "2022-01-22",
            "cases": 0.0,
            "upper": 0.0,
            "lower": 0.0
        },
        {
            "date": "2022-01-23",
            "cases": 0.0,
            "upper": 0.0,
            "lower": 0.0
        },
        {
            "date": "2022-01-24",
            "cases": 0.0,
            "upper": 0.0,
            "lower": 0.0
        },
        {
            "date": "2022-01-25",
            "cases": 0.0,
            "upper": 0.0,
            "lower": 0.0
        },
        {
            "date": "2022-01-26",
            "cases": 0.0,
            "upper": 0.0,
            "lower": 0.0
        },
        {
            "date": "2022-01-27",
            "cases": 0.0,
            "upper": 0.0,
            "lower": 0.0
        },
        {
            "date": "2022-01-28",
            "cases": 0.0,
            "upper": 0.0,
            "lower": 0.0
        },
        {
            "date": "2022-01-29",
            "cases": 0.0,
            "upper": 0.0,
            "lower": 0.0
        },
        {
            "date": "2022-01-30",
            "cases": 0.0,
            "upper": 0.0,
            "lower": 0.0
        },
        {
            "date": "2022-01-31",
            "cases": 0.0,
            "upper": 0.0,
            "lower": 0.0
        },
        {
            "date": "2022-02-01",
            "cases": 0.0,
            "upper": 0.0,
            "lower": 0.0
        }
    ],
    "SHOT_NOISE_FACTOR": 1.8855657641896957
}