{
    "R_eff": 1.1195650401729043,
    "projection": [
        {
            "date": "2021-09-07",
            "cases": 1459.0,
            "upper": 1617.506085036934,
            "lower": 1298.3805004959067
        },
        {
            "date": "2021-09-08",
            "cases": 1479.0,
            "upper": 1667.0938875771617,
            "lower": 1297.2463558243155
        },
        {
            "date": "2021-09-09",
            "cases": 1499.0,
            "upper": 1718.7951045845487,
            "lower": 1285.5451388169288
        },
        {
            "date": "2021-09-10",
            "cases": 1516.0,
            "upper": 1765.3829071247762,
            "lower": 1275.0707507438601
        },
        {
            "date": "2021-09-11",
            "cases": 1529.0,
            "upper": 1816.4243675336406,
            "lower": 1258.4829482036325
        },
        {
            "date": "2021-09-12",
            "cases": 1541.0,
            "upper": 1858.0121700738682,
            "lower": 1243.0085601305639
        },
        {
            "date": "2021-09-13",
            "cases": 1551.0,
            "upper": 1899.713387081255,
            "lower": 1225.5341720574952
        },
        {
            "date": "2021-09-14",
            "cases": 1557.0,
            "upper": 1943.7548474901191,
            "lower": 1206.173198451586
        },
        {
            "date": "2021-09-15",
            "cases": 1560.0,
            "upper": 1982.6828934318241,
            "lower": 1185.9256393128355
        },
        {
            "date": "2021-09-16",
            "cases": 1564.0,
            "upper": 2014.1572815048928,
            "lower": 1153.9975933711305
        },
        {
            "date": "2021-09-17",
            "cases": 1561.0,
            "upper": 2049.198741913757,
            "lower": 1134.0902776338576
        },
        {
            "date": "2021-09-18",
            "cases": 1558.0,
            "upper": 2080.013373388303,
            "lower": 1101.5024750936298
        },
        {
            "date": "2021-09-19",
            "cases": 1551.0,
            "upper": 2094.147518059894,
            "lower": 1077.5951593563568
        },
        {
            "date": "2021-09-20",
            "cases": 1540.0,
            "upper": 2125.4158074030765,
            "lower": 1043.3476002176064
        },
        {
            "date": "2021-09-21",
            "cases": 1525.0,
            "upper": 2133.6633665418267,
            "lower": 1015.6671134146518
        },
        {
            "date": "2021-09-22",
            "cases": 1509.0,
            "upper": 2138.797511213418,
            "lower": 978.5329687430606
        },
        {
            "date": "2021-09-23",
            "cases": 1488.0,
            "upper": 2143.1584848193274,
            "lower": 946.965896407265
        },
        {
            "date": "2021-09-24",
            "cases": 1462.0,
            "upper": 2134.0658005566006,
            "lower": 908.2854096043102
        },
        {
            "date": "2021-09-25",
            "cases": 1437.0,
            "upper": 2132.3133596953508,
            "lower": 874.8317517356737
        },
        {
            "date": "2021-09-26",
            "cases": 1407.0,
            "upper": 2110.7670175639873,
            "lower": 827.9244359984008
        },
        {
            "date": "2021-09-27",
            "cases": 1375.0,
            "upper": 2095.6743333012605,
            "lower": 789.5841925969235
        },
        {
            "date": "2021-09-28",
            "cases": 1338.0,
            "upper": 2065.014576702738,
            "lower": 752.5841925969235
        },
        {
            "date": "2021-09-29",
            "cases": 1302.0,
            "upper": 2037.468234571374,
            "lower": 720.8110215312416
        },
        {
            "date": "2021-09-30",
            "cases": 1262.0,
            "upper": 2005.9218924400107,
            "lower": 682.9244359984008
        },
        {
            "date": "2021-10-01",
            "cases": 1221.0,
            "upper": 1967.0353069071698,
            "lower": 639.8110215312416
        },
        {
            "date": "2021-10-02",
            "cases": 1180.0,
            "upper": 1921.8084779728515,
            "lower": 607.2646793998781
        },
        {
            "date": "2021-10-03",
            "cases": 1137.0,
            "upper": 1878.8084779728515,
            "lower": 566.3780938670373
        },
        {
            "date": "2021-10-04",
            "cases": 1091.0,
            "upper": 1834.9218924400107,
            "lower": 539.3988240714693
        },
        {
            "date": "2021-10-05",
            "cases": 1046.0,
            "upper": 1783.5816490385332,
            "lower": 498.6256530057876
        },
        {
            "date": "2021-10-06",
            "cases": 1001.0,
            "upper": 1719.5609188341014,
            "lower": 468.4195542759014
        },
        {
            "date": "2021-10-07",
            "cases": 955.0,
            "upper": 1665.1072609654648,
            "lower": 439.32687001317436
        },
        {
            "date": "2021-10-08",
            "cases": 910.0,
            "upper": 1605.3133596953508,
            "lower": 402.7805278818109
        },
        {
            "date": "2021-10-09",
            "cases": 863.0,
            "upper": 1537.1792150237598,
            "lower": 372.6878436190839
        },
        {
            "date": "2021-10-10",
            "cases": 816.0,
            "upper": 1479.612142687964,
            "lower": 344.70857382351596
        },
        {
            "date": "2021-10-11",
            "cases": 771.0,
            "upper": 1402.9109256805773,
            "lower": 318.72930402794805
        },
        {
            "date": "2021-10-12",
            "cases": 727.0,
            "upper": 1335.663366541827,
            "lower": 287.40979083090275
        },
        {
            "date": "2021-10-13",
            "cases": 681.0,
            "upper": 1270.6426363373948,
            "lower": 268.88417890397136
        },
        {
            "date": "2021-10-14",
            "cases": 640.0,
            "upper": 1204.2816627314855,
            "lower": 240.56466570692606
        },
        {
            "date": "2021-10-15",
            "cases": 597.0,
            "upper": 1135.9206891255758,
            "lower": 220.81222484567638
        },
        {
            "date": "2021-10-16",
            "cases": 556.0,
            "upper": 1063.219472118189,
            "lower": 196.71954058294938
        },
        {
            "date": "2021-10-17",
            "cases": 516.0,
            "upper": 999.9719129794388,
            "lower": 179.9670997216997
        },
        {
            "date": "2021-10-18",
            "cases": 478.0,
            "upper": 938.7243538406884,
            "lower": 160.98782992613178
        },
        {
            "date": "2021-10-19",
            "cases": 441.0,
            "upper": 874.2499657676199,
            "lower": 145.121974597723
        },
        {
            "date": "2021-10-20",
            "cases": 405.0,
            "upper": 812.8889921617103,
            "lower": 132.36953373647333
        },
        {
            "date": "2021-10-21",
            "cases": 373.0,
            "upper": 755.5280185558009,
            "lower": 117.27684947374632
        },
        {
            "date": "2021-10-22",
            "cases": 341.0,
            "upper": 698.1670449498915,
            "lower": 104.29757967817841
        },
        {
            "date": "2021-10-23",
            "cases": 310.0,
            "upper": 643.9194858111412,
            "lower": 94.43172434976964
        },
        {
            "date": "2021-10-24",
            "cases": 284.0,
            "upper": 588.3316832709135,
            "lower": 81.11221115272434
        },
        {
            "date": "2021-10-25",
            "cases": 257.0,
            "upper": 540.1975385993222,
            "lower": 71.01952688999734
        },
        {
            "date": "2021-10-26",
            "cases": 232.0,
            "upper": 491.9499794605719,
            "lower": 62.926842627270304
        },
        {
            "date": "2021-10-27",
            "cases": 210.0,
            "upper": 448.81583478898074,
            "lower": 55.72074389738415
        },
        {
            "date": "2021-10-28",
            "cases": 189.0,
            "upper": 408.79510458454865,
            "lower": 47.401230700338886
        },
        {
            "date": "2021-10-29",
            "cases": 170.0,
            "upper": 372.88778884727566,
            "lower": 41.08171750329359
        },
        {
            "date": "2021-10-30",
            "cases": 153.0,
            "upper": 336.8670586428435,
            "lower": 34.648789839089204
        },
        {
            "date": "2021-10-31",
            "cases": 137.0,
            "upper": 303.9597429055706,
            "lower": 31.329276642043936
        },
        {
            "date": "2021-11-01",
            "cases": 123.0,
            "upper": 277.2792561026158,
            "lower": 27.896348977839537
        },
        {
            "date": "2021-11-02",
            "cases": 111.0,
            "upper": 248.37194036534288,
            "lower": 22.236592379316903
        },
        {
            "date": "2021-11-03",
            "cases": 99.0,
            "upper": 227.9182824967064,
            "lower": 20.803664715112518
        },
        {
            "date": "2021-11-04",
            "cases": 90.0,
            "upper": 206.23779569375165,
            "lower": 18.14390811658987
        },
        {
            "date": "2021-11-05",
            "cases": 81.0,
            "upper": 186.67072335795606,
            "lower": 13.370737050908119
        },
        {
            "date": "2021-11-06",
            "cases": 73.0,
            "upper": 170.21706548931957,
            "lower": 11.710980452385485
        },
        {
            "date": "2021-11-07",
            "cases": 66.0,
            "upper": 154.7634076206831,
            "lower": 11.051223853862844
        },
        {
            "date": "2021-11-08",
            "cases": 60.0,
            "upper": 140.30974975204663,
            "lower": 9.278052788181085
        },
        {
            "date": "2021-11-09",
            "cases": 54.0,
            "upper": 127.96950635056925,
            "lower": 7.504881722499334
        },
        {
            "date": "2021-11-10",
            "cases": 49.0,
            "upper": 116.62926294909188,
            "lower": 6.731710656817576
        },
        {
            "date": "2021-11-11",
            "cases": 44.0,
            "upper": 107.40243401477363,
            "lower": 5.958539591135818
        },
        {
            "date": "2021-11-12",
            "cases": 40.0,
            "upper": 97.06219061329628,
            "lower": 4.071954058294935
        },
        {
            "date": "2021-11-13",
            "cases": 36.0,
            "upper": 88.83536167897803,
            "lower": 4.29878299261318
        },
        {
            "date": "2021-11-14",
            "cases": 33.0,
            "upper": 81.60853274465978,
            "lower": 1.2987829926131802
        },
        {
            "date": "2021-11-15",
            "cases": 30.0,
            "upper": 74.38170381034155,
            "lower": 0.41219745977230104
        },
        {
            "date": "2021-11-16",
            "cases": 27.0,
            "upper": 67.15487487602331,
            "lower": 1.6390263940905427
        },
        {
            "date": "2021-11-17",
            "cases": 24.0,
            "upper": 62.04146040886418,
            "lower": 0.7524408612496671
        },
        {
            "date": "2021-11-18",
            "cases": 22.0,
            "upper": 57.928045941705065,
            "lower": 0.865855328408788
        },
        {
            "date": "2021-11-19",
            "cases": 20.0,
            "upper": 51.701217007386816,
            "lower": 0.9792697955679088
        },
        {
            "date": "2021-11-20",
            "cases": 18.0,
            "upper": 47.5878025402277,
            "lower": -1.0207302044320912
        },
        {
            "date": "2021-11-21",
            "cases": 16.0,
            "upper": 43.47438807306858,
            "lower": -0.9073157372729703
        },
        {
            "date": "2021-11-22",
            "cases": 15.0,
            "upper": 40.36097360590946,
            "lower": -1.9073157372729703
        },
        {
            "date": "2021-11-23",
            "cases": 13.0,
            "upper": 36.24755913875033,
            "lower": 0.31951319704527137
        },
        {
            "date": "2021-11-24",
            "cases": 12.0,
            "upper": 33.134144671591216,
            "lower": -0.6804868029547286
        },
        {
            "date": "2021-11-25",
            "cases": 11.0,
            "upper": 30.02073020443209,
            "lower": -1.6804868029547286
        },
        {
            "date": "2021-11-26",
            "cases": 10.0,
            "upper": 29.02073020443209,
            "lower": -0.567072335795606
        },
        {
            "date": "2021-11-27",
            "cases": 9.0,
            "upper": 25.90731573727297,
            "lower": -1.567072335795606
        },
        {
            "date": "2021-11-28",
            "cases": 8.0,
            "upper": 24.90731573727297,
            "lower": -2.567072335795606
        },
        {
            "date": "2021-11-29",
            "cases": 7.0,
            "upper": 21.79390127011385,
            "lower": -1.4536578686364852
        },
        {
            "date": "2021-11-30",
            "cases": 6.0,
            "upper": 20.79390127011385,
            "lower": -0.3402434014773643
        },
        {
            "date": "2021-12-01",
            "cases": 6.0,
            "upper": 18.68048680295473,
            "lower": -2.453657868636485
        },
        {
            "date": "2021-12-02",
            "cases": 5.0,
            "upper": 17.68048680295473,
            "lower": -1.3402434014773643
        },
        {
            "date": "2021-12-03",
            "cases": 5.0,
            "upper": 15.567072335795606,
            "lower": -1.3402434014773643
        },
        {
            "date": "2021-12-04",
            "cases": 4.0,
            "upper": 14.567072335795606,
            "lower": -2.3402434014773643
        },
        {
            "date": "2021-12-05",
            "cases": 4.0,
            "upper": 12.453657868636485,
            "lower": -2.3402434014773643
        },
        {
            "date": "2021-12-06",
            "cases": 3.0,
            "upper": 13.567072335795606,
            "lower": -1.2268289343182426
        },
        {
            "date": "2021-12-07",
            "cases": 3.0,
            "upper": 11.453657868636485,
            "lower": -1.2268289343182426
        },
        {
            "date": "2021-12-08",
            "cases": 3.0,
            "upper": 9.340243401477364,
            "lower": -1.2268289343182426
        },
        {
            "date": "2021-12-09",
            "cases": 3.0,
            "upper": 9.340243401477364,
            "lower": -1.2268289343182426
        },
        {
            "date": "2021-12-10",
            "cases": 2.0,
            "upper": 8.340243401477364,
            "lower": -2.2268289343182426
        },
        {
            "date": "2021-12-11",
            "cases": 2.0,
            "upper": 8.340243401477364,
            "lower": -2.2268289343182426
        },
        {
            "date": "2021-12-12",
            "cases": 2.0,
            "upper": 8.340243401477364,
            "lower": -2.2268289343182426
        },
        {
            "date": "2021-12-13",
            "cases": 2.0,
            "upper": 6.226828934318243,
            "lower": -2.2268289343182426
        },
        {
            "date": "2021-12-14",
            "cases": 1.0,
            "upper": 7.340243401477364,
            "lower": -1.1134144671591213
        },
        {
            "date": "2021-12-15",
            "cases": 1.0,
            "upper": 7.340243401477364,
            "lower": -1.1134144671591213
        },
        {
            "date": "2021-12-16",
            "cases": 1.0,
            "upper": 5.226828934318243,
            "lower": -1.1134144671591213
        },
        {
            "date": "2021-12-17",
            "cases": 1.0,
            "upper": 5.226828934318243,
            "lower": -1.1134144671591213
        },
        {
            "date": "2021-12-18",
            "cases": 1.0,
            "upper": 5.226828934318243,
            "lower": -1.1134144671591213
        },
        {
            "date": "2021-12-19",
            "cases": 1.0,
            "upper": 5.226828934318243,
            "lower": -1.1134144671591213
        },
        {
            "date": "2021-12-20",
            "cases": 1.0,
            "upper": 3.1134144671591213,
            "lower": -1.1134144671591213
        },
        {
            "date": "2021-12-21",
            "cases": 1.0,
            "upper": 3.1134144671591213,
            "lower": -1.1134144671591213
        },
        {
            "date": "2021-12-22",
            "cases": 0.0,
            "upper": 4.226828934318243,
            "lower": 0.0
        },
        {
            "date": "2021-12-23",
            "cases": 0.0,
            "upper": 4.226828934318243,
            "lower": 0.0
        },
        {
            "date": "2021-12-24",
            "cases": 0.0,
            "upper": 4.226828934318243,
            "lower": 0.0
        },
        {
            "date": "2021-12-25",
            "cases": 0.0,
            "upper": 4.226828934318243,
            "lower": 0.0
        },
        {
            "date": "2021-12-26",
            "cases": 0.0,
            "upper": 2.1134144671591213,
            "lower": 0.0
        },
        {
            "date": "2021-12-27",
            "cases": 0.0,
            "upper": 2.1134144671591213,
            "lower": 0.0
        },
        {
            "date": "2021-12-28",
            "cases": 0.0,
            "upper": 2.1134144671591213,
            "lower": 0.0
        },
        {
            "date": "2021-12-29",
            "cases": 0.0,
            "upper": 2.1134144671591213,
            "lower": 0.0
        },
        {
            "date": "2021-12-30",
            "cases": 0.0,
            "upper": 2.1134144671591213,
            "lower": 0.0
        },
        {
            "date": "2021-12-31",
            "cases": 0.0,
            "upper": 2.1134144671591213,
            "lower": 0.0
        },
        {
            "date": "2022-01-01",
            "cases": 0.0,
            "upper": 2.1134144671591213,
            "lower": 0.0
        },
        {
            "date": "2022-01-02",
            "cases": 0.0,
            "upper": 2.1134144671591213,
            "lower": 0.0
        },
        {
            "date": "2022-01-03",
            "cases": 0.0,
            "upper": 2.1134144671591213,
            "lower": 0.0
        },
        {
            "date": "2022-01-04",
            "cases": 0.0,
            "upper": 2.1134144671591213,
            "lower": 0.0
        },
        {
            "date": "2022-01-05",
            "cases": 0.0,
            "upper": 2.1134144671591213,
            "lower": 0.0
        },
        {
            "date": "2022-01-06",
            "cases": 0.0,
            "upper": 2.1134144671591213,
            "lower": 0.0
        },
        {
            "date": "2022-01-07",
            "cases": 0.0,
            "upper": 0.0,
            "lower": 0.0
        },
        {
            "date": "2022-01-08",
            "cases": 0.0,
            "upper": 0.0,
            "lower": 0.0
        },
        {
            "date": "2022-01-09",
            "cases": 0.0,
            "upper": 0.0,
            "lower": 0.0
        },
        {
            "date": "2022-01-10",
            "cases": 0.0,
            "upper": 0.0,
            "lower": 0.0
        },
        {
            "date": "2022-01-11",
            "cases": 0.0,
            "upper": 0.0,
            "lower": 0.0
        },
        {
            "date": "2022-01-12",
            "cases": 0.0,
            "upper": 0.0,
            "lower": 0.0
        },
        {
            "date": "2022-01-13",
            "cases": 0.0,
            "upper": 0.0,
            "lower": 0.0
        },
        {
            "date": "2022-01-14",
            "cases": 0.0,
            "upper": 0.0,
            "lower": 0.0
        },
        {
            "date": "2022-01-15",
            "cases": 0.0,
            "upper": 0.0,
            "lower": 0.0
        },
        {
            "date": "2022-01-16",
            "cases": 0.0,
            "upper": 0.0,
            "lower": 0.0
        },
        {
            "date": "2022-01-17",
            "cases": 0.0,
            "upper": 0.0,
            "lower": 0.0
        },
        {
            "date": "2022-01-18",
            "cases": 0.0,
            "upper": 0.0,
            "lower": 0.0
        },
        {
            "date": "2022-01-19",
            "cases": 0.0,
            "upper": 0.0,
            "lower": 0.0
        },
        {
            "date": "2022-01-20",
            "cases": 0.0,
            "upper": 0.0,
            "lower": 0.0
        },
        {
            "date": "2022-01-21",
            "cases": 0.0,
            "upper": 0.0,
            "lower": 0.0
        },
        {
            "date": "2022-01-22",
            "cases": 0.0,
            "upper": 0.0,
            "lower": 0.0
        },
        {
            "date": "2022-01-23",
            "cases": 0.0,
            "upper": 0.0,
            "lower": 0.0
        },
        {
            "date": "2022-01-24",
            "cases": 0.0,
            "upper": 0.0,
            "lower": 0.0
        },
        {
            "date": "2022-01-25",
            "cases": 0.0,
            "upper": 0.0,
            "lower": 0.0
        },
        {
            "date": "2022-01-26",
            "cases": 0.0,
            "upper": 0.0,
            "lower": 0.0
        },
        {
            "date": "2022-01-27",
            "cases": 0.0,
            "upper": 0.0,
            "lower": 0.0
        },
        {
            "date": "2022-01-28",
            "cases": 0.0,
            "upper": 0.0,
            "lower": 0.0
        },
        {
            "date": "2022-01-29",
            "cases": 0.0,
            "upper": 0.0,
            "lower": 0.0
        },
        {
            "date": "2022-01-30",
            "cases": 0.0,
            "upper": 0.0,
            "lower": 0.0
        },
        {
            "date": "2022-01-31",
            "cases": 0.0,
            "upper": 0.0,
            "lower": 0.0
        },
        {
            "date": "2022-02-01",
            "cases": 0.0,
            "upper": 0.0,
            "lower": 0.0
        }
    ],
    "SHOT_NOISE_FACTOR": 2.1134144671591213,
    "R_eff_others": 1.2834324195429514,
    "R_eff_concern": 1.126444625829191,
    "u_R_eff_others": 0.07035344830268198,
    "u_R_eff_concern": 0.052897718406822,
    "u_R_eff": 0.04931237490201301,
    "today": "2021-09-08"
}