{
    "R_eff": 0.9829919739837921,
    "u_R_eff": 0.08030212327705166,
    "today": "2022-01-20",
    "projection": [
        {
            "date": "2022-01-19",
            "cases": 17518.0,
            "upper": 21311.24327329524,
            "lower": 13899.006825168126
        },
        {
            "date": "2022-01-20",
            "cases": 17141.0,
            "upper": 21123.263626699816,
            "lower": 13371.412781861021
        },
        {
            "date": "2022-01-21",
            "cases": 16704.0,
            "upper": 20845.978497386233,
            "lower": 12822.201718360615
        },
        {
            "date": "2022-01-22",
            "cases": 16228.0,
            "upper": 20529.2438441346,
            "lower": 12256.160299820938
        },
        {
            "date": "2022-01-23",
            "cases": 15699.0,
            "upper": 20120.875254335297,
            "lower": 11670.647569351837
        },
        {
            "date": "2022-01-24",
            "cases": 15146.0,
            "upper": 19641.982172090185,
            "lower": 11077.869919352943
        },
        {
            "date": "2022-01-25",
            "cases": 14567.0,
            "upper": 19125.42016072859,
            "lower": 10491.808123988689
        },
        {
            "date": "2022-01-26",
            "cases": 13968.0,
            "upper": 18551.874799074947,
            "lower": 9912.517876958085
        },
        {
            "date": "2022-01-27",
            "cases": 13361.0,
            "upper": 17951.046494738057,
            "lower": 9329.031106228242
        },
        {
            "date": "2022-01-28",
            "cases": 12747.0,
            "upper": 17314.259328026605,
            "lower": 8751.589177503307
        },
        {
            "date": "2022-01-29",
            "cases": 12132.0,
            "upper": 16641.337411659613,
            "lower": 8217.77473106464
        },
        {
            "date": "2022-01-30",
            "cases": 11525.0,
            "upper": 15983.539505890276,
            "lower": 7688.164232046711
        },
        {
            "date": "2022-01-31",
            "cases": 10910.0,
            "upper": 15278.594337236264,
            "lower": 7176.506353655406
        },
        {
            "date": "2022-02-01",
            "cases": 10336.0,
            "upper": 14576.753701877482,
            "lower": 6696.387882985507
        },
        {
            "date": "2022-02-02",
            "cases": 9750.0,
            "upper": 13880.102886865912,
            "lower": 6216.961577045526
        },
        {
            "date": "2022-02-03",
            "cases": 9185.0,
            "upper": 13186.415648146201,
            "lower": 5772.589040384265
        },
        {
            "date": "2022-02-04",
            "cases": 8634.0,
            "upper": 12491.273599286125,
            "lower": 5343.349158304032
        },
        {
            "date": "2022-02-05",
            "cases": 8120.0,
            "upper": 11809.731589683372,
            "lower": 4944.429296395538
        },
        {
            "date": "2022-02-06",
            "cases": 7610.0,
            "upper": 11179.812055343875,
            "lower": 4565.870756216242
        },
        {
            "date": "2022-02-07",
            "cases": 7127.0,
            "upper": 10547.256602051648,
            "lower": 4215.56609373705
        },
        {
            "date": "2022-02-08",
            "cases": 6665.0,
            "upper": 9925.021340183477,
            "lower": 3873.067811862486
        },
        {
            "date": "2022-02-09",
            "cases": 6228.0,
            "upper": 9333.867051773648,
            "lower": 3555.9885251866735
        },
        {
            "date": "2022-02-10",
            "cases": 5811.0,
            "upper": 8771.708236927834,
            "lower": 3263.272419622326
        },
        {
            "date": "2022-02-11",
            "cases": 5411.0,
            "upper": 8223.20678577911,
            "lower": 2987.7962517301075
        },
        {
            "date": "2022-02-12",
            "cases": 5035.0,
            "upper": 7715.9993078064035,
            "lower": 2728.608313044938
        },
        {
            "date": "2022-02-13",
            "cases": 4678.0,
            "upper": 7231.456781507688,
            "lower": 2489.9013517888193
        },
        {
            "date": "2022-02-14",
            "cases": 4344.0,
            "upper": 6752.930064882111,
            "lower": 2266.3893293802716
        },
        {
            "date": "2022-02-15",
            "cases": 4027.0,
            "upper": 6326.199940937092,
            "lower": 2060.505050638707
        },
        {
            "date": "2022-02-16",
            "cases": 3742.0,
            "upper": 5903.383246900334,
            "lower": 1872.0781424565166
        },
        {
            "date": "2022-02-17",
            "cases": 3464.0,
            "upper": 5509.183532849222,
            "lower": 1695.0967986090157
        },
        {
            "date": "2022-02-18",
            "cases": 3207.0,
            "upper": 5148.333292316785,
            "lower": 1536.9122469689787
        },
        {
            "date": "2022-02-19",
            "cases": 2965.0,
            "upper": 4800.614191514184,
            "lower": 1378.446778242606
        },
        {
            "date": "2022-02-20",
            "cases": 2745.0,
            "upper": 4466.042593882816,
            "lower": 1241.7789879915167
        },
        {
            "date": "2022-02-21",
            "cases": 2534.0,
            "upper": 4164.202202008537,
            "lower": 1113.666369956401
        },
        {
            "date": "2022-02-22",
            "cases": 2336.0,
            "upper": 3880.399635062715,
            "lower": 997.2229178980391
        },
        {
            "date": "2022-02-23",
            "cases": 2152.0,
            "upper": 3610.113901726815,
            "lower": 888.3510385382067
        },
        {
            "date": "2022-02-24",
            "cases": 1984.0,
            "upper": 3361.6048930466422,
            "lower": 790.8676077283471
        },
        {
            "date": "2022-02-25",
            "cases": 1829.0,
            "upper": 3126.862592585464,
            "lower": 701.49539552784
        },
        {
            "date": "2022-02-26",
            "cases": 1685.0,
            "upper": 2910.7286643044677,
            "lower": 620.8702919592431
        },
        {
            "date": "2022-02-27",
            "cases": 1548.0,
            "upper": 2703.8730728608643,
            "lower": 545.844989455505
        },
        {
            "date": "2022-02-28",
            "cases": 1422.0,
            "upper": 2514.744153561377,
            "lower": 476.36443091170156
        },
        {
            "date": "2022-03-01",
            "cases": 1307.0,
            "upper": 2337.5252546331576,
            "lower": 414.52792811144013
        },
        {
            "date": "2022-03-02",
            "cases": 1202.0,
            "upper": 2178.4366298469417,
            "lower": 358.7285024360309
        },
        {
            "date": "2022-03-03",
            "cases": 1102.0,
            "upper": 2025.4780144794972,
            "lower": 308.83201416636246
        },
        {
            "date": "2022-03-04",
            "cases": 1011.0,
            "upper": 1881.1452677336524,
            "lower": 262.6387375054869
        },
        {
            "date": "2022-03-05",
            "cases": 927.0,
            "upper": 1748.026025914423,
            "lower": 220.773902445901
        },
        {
            "date": "2022-03-06",
            "cases": 850.0,
            "upper": 1625.03021872428,
            "lower": 184.44572130892453
        },
        {
            "date": "2022-03-07",
            "cases": 779.0,
            "upper": 1507.225204682883,
            "lower": 149.62644694682984
        },
        {
            "date": "2022-03-08",
            "cases": 712.0,
            "upper": 1402.3529892538281,
            "lower": 120.10410656511556
        },
        {
            "date": "2022-03-09",
            "cases": 652.0,
            "upper": 1304.1964982025272,
            "lower": 93.22432580419434
        },
        {
            "date": "2022-03-10",
            "cases": 596.0,
            "upper": 1211.5459400072505,
            "lower": 70.10066531302311
        },
        {
            "date": "2022-03-11",
            "cases": 544.0,
            "upper": 1124.47525336187,
            "lower": 48.86151125395395
        },
        {
            "date": "2022-03-12",
            "cases": 499.0,
            "upper": 1047.0972761155472,
            "lower": 30.032485713643155
        },
        {
            "date": "2022-03-13",
            "cases": 456.0,
            "upper": 972.8678577925058,
            "lower": 13.004156335662913
        },
        {
            "date": "2022-03-14",
            "cases": 415.0,
            "upper": 907.3084208380061,
            "lower": 0
        },
        {
            "date": "2022-03-15",
            "cases": 378.0,
            "upper": 839.5234966261922,
            "lower": 0
        },
        {
            "date": "2022-03-16",
            "cases": 345.0,
            "upper": 783.4494885826985,
            "lower": 0
        },
        {
            "date": "2022-03-17",
            "cases": 314.0,
            "upper": 728.0400484206316,
            "lower": 0
        },
        {
            "date": "2022-03-18",
            "cases": 285.0,
            "upper": 679.0529175412431,
            "lower": 0
        },
        {
            "date": "2022-03-19",
            "cases": 260.0,
            "upper": 630.807261963857,
            "lower": 0
        },
        {
            "date": "2022-03-20",
            "cases": 236.0,
            "upper": 587.7548763874622,
            "lower": 0
        },
        {
            "date": "2022-03-21",
            "cases": 215.0,
            "upper": 547.0361857940503,
            "lower": 0
        },
        {
            "date": "2022-03-22",
            "cases": 195.0,
            "upper": 510.24903536878014,
            "lower": 0
        },
        {
            "date": "2022-03-23",
            "cases": 177.0,
            "upper": 475.9625137025028,
            "lower": 0
        },
        {
            "date": "2022-03-24",
            "cases": 161.0,
            "upper": 444.25280509491677,
            "lower": 0
        },
        {
            "date": "2022-03-25",
            "cases": 146.0,
            "upper": 413.5784283624651,
            "lower": 0
        },
        {
            "date": "2022-03-26",
            "cases": 132.0,
            "upper": 385.60750295658613,
            "lower": 0
        },
        {
            "date": "2022-03-27",
            "cases": 120.0,
            "upper": 360.4505974269907,
            "lower": 0
        },
        {
            "date": "2022-03-28",
            "cases": 109.0,
            "upper": 336.5048295398049,
            "lower": 0
        },
        {
            "date": "2022-03-29",
            "cases": 98.0,
            "upper": 315.5671927060471,
            "lower": 0
        },
        {
            "date": "2022-03-30",
            "cases": 89.0,
            "upper": 294.1892183934265,
            "lower": 0
        },
        {
            "date": "2022-03-31",
            "cases": 81.0,
            "upper": 275.98631294744587,
            "lower": 0
        },
        {
            "date": "2022-04-01",
            "cases": 73.0,
            "upper": 259.255931547916,
            "lower": 0
        },
        {
            "date": "2022-04-02",
            "cases": 67.0,
            "upper": 242.14573286089353,
            "lower": 0
        },
        {
            "date": "2022-04-03",
            "cases": 60.0,
            "upper": 228.53602053986597,
            "lower": 0
        },
        {
            "date": "2022-04-04",
            "cases": 55.0,
            "upper": 214.62244115586736,
            "lower": 0
        },
        {
            "date": "2022-04-05",
            "cases": 50.0,
            "upper": 200.3587830950475,
            "lower": 0
        },
        {
            "date": "2022-04-06",
            "cases": 45.0,
            "upper": 189.92396086938274,
            "lower": 0
        },
        {
            "date": "2022-04-07",
            "cases": 41.0,
            "upper": 179.25354019864315,
            "lower": 0
        },
        {
            "date": "2022-04-08",
            "cases": 37.0,
            "upper": 168.31393520816655,
            "lower": 0
        },
        {
            "date": "2022-04-09",
            "cases": 34.0,
            "upper": 159.34031562362827,
            "lower": 0
        },
        {
            "date": "2022-04-10",
            "cases": 30.0,
            "upper": 147.8010833873036,
            "lower": 0
        },
        {
            "date": "2022-04-11",
            "cases": 28.0,
            "upper": 140.67976206095216,
            "lower": 0
        },
        {
            "date": "2022-04-12",
            "cases": 25.0,
            "upper": 133.38768808335834,
            "lower": 0
        },
        {
            "date": "2022-04-13",
            "cases": 23.0,
            "upper": 125.90169663443429,
            "lower": 0
        },
        {
            "date": "2022-04-14",
            "cases": 21.0,
            "upper": 118.19285728722352,
            "lower": 0
        },
        {
            "date": "2022-04-15",
            "cases": 19.0,
            "upper": 112.91201198142664,
            "lower": 0
        },
        {
            "date": "2022-04-16",
            "cases": 17.0,
            "upper": 107.50236013242876,
            "lower": 0
        },
        {
            "date": "2022-04-17",
            "cases": 15.0,
            "upper": 101.94742315241943,
            "lower": 0
        },
        {
            "date": "2022-04-18",
            "cases": 14.0,
            "upper": 96.22687708241885,
            "lower": 0
        },
        {
            "date": "2022-04-19",
            "cases": 12.0,
            "upper": 90.31516515064023,
            "lower": 0
        },
        {
            "date": "2022-04-20",
            "cases": 11.0,
            "upper": 87.27770821019608,
            "lower": 0
        },
        {
            "date": "2022-04-21",
            "cases": 10.0,
            "upper": 81.01441200452855,
            "lower": 0
        },
        {
            "date": "2022-04-22",
            "cases": 9.0,
            "upper": 77.77598100238626,
            "lower": 0
        },
        {
            "date": "2022-04-23",
            "cases": 8.0,
            "upper": 74.45607303863324,
            "lower": 0
        },
        {
            "date": "2022-04-24",
            "cases": 8.0,
            "upper": 71.0450850947216,
            "lower": 0
        },
        {
            "date": "2022-04-25",
            "cases": 7.0,
            "upper": 67.53136504946616,
            "lower": 0
        },
        {
            "date": "2022-04-26",
            "cases": 6.0,
            "upper": 63.900541693651796,
            "lower": 0
        },
        {
            "date": "2022-04-27",
            "cases": 6.0,
            "upper": 60.13454366064281,
            "lower": 0
        },
        {
            "date": "2022-04-28",
            "cases": 5.0,
            "upper": 56.210110100426824,
            "lower": 0
        },
        {
            "date": "2022-04-29",
            "cases": 4.0,
            "upper": 56.210110100426824,
            "lower": 0
        },
        {
            "date": "2022-04-30",
            "cases": 4.0,
            "upper": 52.09642864361176,
            "lower": 0
        },
        {
            "date": "2022-05-01",
            "cases": 4.0,
            "upper": 52.09642864361176,
            "lower": 0
        }
    ],
    "SHOT_NOISE_FACTOR": 17.044847886880937
}