{
    "R_eff": 1.9960089970757642,
    "projection": [
        {
            "date": "2021-12-29",
            "cases": 11189.0,
            "upper": 12201.71718566633,
            "lower": 10196.462179588461
        },
        {
            "date": "2021-12-30",
            "cases": 12632.0,
            "upper": 13873.44019748948,
            "lower": 11434.485003286856
        },
        {
            "date": "2021-12-31",
            "cases": 14220.0,
            "upper": 15723.351100230497,
            "lower": 12763.141079297771
        },
        {
            "date": "2022-01-01",
            "cases": 15932.0,
            "upper": 17758.355210641927,
            "lower": 14208.03545628949
        },
        {
            "date": "2022-01-02",
            "cases": 17785.0,
            "upper": 19940.709698071165,
            "lower": 15734.854767899635
        },
        {
            "date": "2022-01-03",
            "cases": 19743.0,
            "upper": 22291.65707218169,
            "lower": 17385.93581285817
        },
        {
            "date": "2022-01-04",
            "cases": 21829.0,
            "upper": 24756.37554846494,
            "lower": 19069.769486178506
        },
        {
            "date": "2022-01-05",
            "cases": 23984.0,
            "upper": 27356.16872905123,
            "lower": 20833.571595665453
        },
        {
            "date": "2022-01-06",
            "cases": 26161.0,
            "upper": 29994.862340056163,
            "lower": 22631.978242475612
        },
        {
            "date": "2022-01-07",
            "cases": 28381.0,
            "upper": 32589.636906590313,
            "lower": 24419.528619732006
        },
        {
            "date": "2022-01-08",
            "cases": 30502.0,
            "upper": 35131.61842021883,
            "lower": 26171.42068409778
        },
        {
            "date": "2022-01-09",
            "cases": 32528.0,
            "upper": 37507.775162778584,
            "lower": 27880.610164111877
        },
        {
            "date": "2022-01-10",
            "cases": 34391.0,
            "upper": 39633.48108610625,
            "lower": 29450.16317681577
        },
        {
            "date": "2022-01-11",
            "cases": 36018.0,
            "upper": 41431.21269106636,
            "lower": 30810.721045454415
        },
        {
            "date": "2022-01-12",
            "cases": 37362.0,
            "upper": 42805.25716098521,
            "lower": 32020.40454313048
        },
        {
            "date": "2022-01-13",
            "cases": 38344.0,
            "upper": 43722.507486866496,
            "lower": 32974.30489575986
        },
        {
            "date": "2022-01-14",
            "cases": 38951.0,
            "upper": 44124.53123150131,
            "lower": 33701.945554342026
        },
        {
            "date": "2022-01-15",
            "cases": 39151.0,
            "upper": 44020.49169246247,
            "lower": 34071.731921638726
        },
        {
            "date": "2022-01-16",
            "cases": 38973.0,
            "upper": 43406.32994170659,
            "lower": 34208.18287249213
        },
        {
            "date": "2022-01-17",
            "cases": 38389.0,
            "upper": 42334.4708624196,
            "lower": 33991.64257459016
        },
        {
            "date": "2022-01-18",
            "cases": 37470.0,
            "upper": 40827.973331123576,
            "lower": 33499.26486417955
        },
        {
            "date": "2022-01-19",
            "cases": 36212.0,
            "upper": 38993.71280336819,
            "lower": 32762.75253342583
        },
        {
            "date": "2022-01-20",
            "cases": 34699.0,
            "upper": 36870.847169697125,
            "lower": 31741.678926965218
        },
        {
            "date": "2022-01-21",
            "cases": 32974.0,
            "upper": 34573.3457352341,
            "lower": 30574.548720374194
        },
        {
            "date": "2022-01-22",
            "cases": 30998.0,
            "upper": 32249.676460622253,
            "lower": 29190.345911995955
        },
        {
            "date": "2022-01-23",
            "cases": 28911.0,
            "upper": 30041.426071089358,
            "lower": 27547.80346667726
        },
        {
            "date": "2022-01-24",
            "cases": 26878.0,
            "upper": 27960.794652168104,
            "lower": 25612.703941653028
        },
        {
            "date": "2022-01-25",
            "cases": 24932.0,
            "upper": 26023.051112237277,
            "lower": 23565.099469659057
        },
        {
            "date": "2022-01-26",
            "cases": 23056.0,
            "upper": 24202.956171970294,
            "lower": 21455.598872117433
        },
        {
            "date": "2022-01-27",
            "cases": 21198.0,
            "upper": 22491.457736613538,
            "lower": 19418.496709582647
        },
        {
            "date": "2022-01-28",
            "cases": 19402.0,
            "upper": 20855.14000488492,
            "lower": 17507.01315146869
        },
        {
            "date": "2022-01-29",
            "cases": 17667.0,
            "upper": 19285.9023305196,
            "lower": 15739.772545385189
        },
        {
            "date": "2022-01-30",
            "cases": 16056.0,
            "upper": 17775.62699495691,
            "lower": 14102.889045816008
        },
        {
            "date": "2022-01-31",
            "cases": 14549.0,
            "upper": 16317.192167055948,
            "lower": 12617.846192575355
        },
        {
            "date": "2022-02-01",
            "cases": 13155.0,
            "upper": 14960.431215187591,
            "lower": 11263.844444837583
        },
        {
            "date": "2022-02-02",
            "cases": 11875.0,
            "upper": 13668.782351528294,
            "lower": 10054.422634663739
        },
        {
            "date": "2022-02-03",
            "cases": 10711.0,
            "upper": 12471.817552759876,
            "lower": 8960.951281615076
        },
        {
            "date": "2022-02-04",
            "cases": 9646.0,
            "upper": 11371.67972040539,
            "lower": 7977.374916770503
        },
        {
            "date": "2022-02-05",
            "cases": 8683.0,
            "upper": 10357.262789208668,
            "lower": 7098.6098339938735
        },
        {
            "date": "2022-02-06",
            "cases": 7810.0,
            "upper": 9426.633377375249,
            "lower": 6302.0263090055405
        },
        {
            "date": "2022-02-07",
            "cases": 7012.0,
            "upper": 8555.35719491815,
            "lower": 5601.087089634896
        },
        {
            "date": "2022-02-08",
            "cases": 6292.0,
            "upper": 7775.24693814789,
            "lower": 4971.259428704119
        },
        {
            "date": "2022-02-09",
            "cases": 5645.0,
            "upper": 7043.411856448995,
            "lower": 4411.4054800148815
        },
        {
            "date": "2022-02-10",
            "cases": 5068.0,
            "upper": 6389.679338919911,
            "lower": 3912.622572134296
        },
        {
            "date": "2022-02-11",
            "cases": 4547.0,
            "upper": 5793.661193857013,
            "lower": 3473.7686292906264
        },
        {
            "date": "2022-02-12",
            "cases": 4072.0,
            "upper": 5258.562969711203,
            "lower": 3079.224482382007
        },
        {
            "date": "2022-02-13",
            "cases": 3656.0,
            "upper": 4760.812794205821,
            "lower": 2728.8588921160044
        },
        {
            "date": "2022-02-14",
            "cases": 3279.0,
            "upper": 4312.864511138247,
            "lower": 2410.0474815470498
        },
        {
            "date": "2022-02-15",
            "cases": 2934.0,
            "upper": 3910.7116233515417,
            "lower": 2138.008155051845
        },
        {
            "date": "2022-02-16",
            "cases": 2630.0,
            "upper": 3546.19239824594,
            "lower": 1894.3825589956123
        },
        {
            "date": "2022-02-17",
            "cases": 2357.0,
            "upper": 3209.0266475358894,
            "lower": 1675.2547595449514
        },
        {
            "date": "2022-02-18",
            "cases": 2113.0,
            "upper": 2902.395239123565,
            "lower": 1480.5286420957882
        },
        {
            "date": "2022-02-19",
            "cases": 1891.0,
            "upper": 2629.516421497262,
            "lower": 1310.0895607714413
        },
        {
            "date": "2022-02-20",
            "cases": 1695.0,
            "upper": 2384.246329556566,
            "lower": 1153.4405083998624
        },
        {
            "date": "2022-02-21",
            "cases": 1518.0,
            "upper": 2161.4495905307026,
            "lower": 1022.7392702189345
        },
        {
            "date": "2022-02-22",
            "cases": 1359.0,
            "upper": 1962.2543876148086,
            "lower": 902.8311681087642
        },
        {
            "date": "2022-02-23",
            "cases": 1217.0,
            "upper": 1773.0797534378326,
            "lower": 794.6076513555698
        },
        {
            "date": "2022-02-24",
            "cases": 1088.0,
            "upper": 1607.647515726791,
            "lower": 701.7143573851506
        },
        {
            "date": "2022-02-25",
            "cases": 975.0,
            "upper": 1455.5014117008598,
            "lower": 616.6453568692459
        },
        {
            "date": "2022-02-26",
            "cases": 873.0,
            "upper": 1319.8737438339294,
            "lower": 543.954509077038
        },
        {
            "date": "2022-02-27",
            "cases": 783.0,
            "upper": 1198.7225476524322,
            "lower": 478.9603389332416
        },
        {
            "date": "2022-02-28",
            "cases": 700.0,
            "upper": 1086.7877946072008,
            "lower": 420.6978420118187
        },
        {
            "date": "2022-03-01",
            "cases": 627.0,
            "upper": 988.3916971640891,
            "lower": 369.1156200828281
        },
        {
            "date": "2022-03-02",
            "cases": 562.0,
            "upper": 898.2474485990112,
            "lower": 323.2561939170931
        },
        {
            "date": "2022-03-03",
            "cases": 504.0,
            "upper": 813.1594629827579,
            "lower": 283.9560382482755
        },
        {
            "date": "2022-03-04",
            "cases": 451.0,
            "upper": 739.6385698141493,
            "lower": 248.48201576206617
        },
        {
            "date": "2022-03-05",
            "cases": 405.0,
            "upper": 670.1648423405026,
            "lower": 216.80096165842426
        },
        {
            "date": "2022-03-06",
            "cases": 361.0,
            "upper": 609.1172845687194,
            "lower": 187.1356322721357
        },
        {
            "date": "2022-03-07",
            "cases": 324.0,
            "upper": 555.4699521030442,
            "lower": 163.7892690304856
        },
        {
            "date": "2022-03-08",
            "cases": 289.0,
            "upper": 504.8785880388341,
            "lower": 143.22413038717133
        },
        {
            "date": "2022-03-09",
            "cases": 260.0,
            "upper": 457.35266912509235,
            "lower": 124.55607951500002
        },
        {
            "date": "2022-03-10",
            "cases": 233.0,
            "upper": 418.47383840961976,
            "lower": 106.93137011187424
        },
        {
            "date": "2022-03-11",
            "cases": 209.0,
            "upper": 379.39028888117963,
            "lower": 92.82979187163144
        },
        {
            "date": "2022-03-12",
            "cases": 186.0,
            "upper": 345.6999433278102,
            "lower": 78.90626274030947
        },
        {
            "date": "2022-03-13",
            "cases": 166.0,
            "upper": 315.2029828478538,
            "lower": 68.40182311483147
        },
        {
            "date": "2022-03-14",
            "cases": 150.0,
            "upper": 287.9316535316115,
            "lower": 58.04556431225899
        },
        {
            "date": "2022-03-15",
            "cases": 134.0,
            "upper": 262.77586961282867,
            "lower": 49.42026453157691
        },
        {
            "date": "2022-03-16",
            "cases": 120.0,
            "upper": 239.75490862643105,
            "lower": 41.710081893859446
        },
        {
            "date": "2022-03-17",
            "cases": 108.0,
            "upper": 218.89144841156818,
            "lower": 35.64856412459989
        },
        {
            "date": "2022-03-18",
            "cases": 96.0,
            "upper": 200.21191525491335,
            "lower": 28.965044304500516
        },
        {
            "date": "2022-03-19",
            "cases": 87.0,
            "upper": 181.38421556929634,
            "lower": 23.885757752562284
        },
        {
            "date": "2022-03-20",
            "cases": 77.0,
            "upper": 167.1498792565151,
            "lower": 19.631895018581297
        },
        {
            "date": "2022-03-21",
            "cases": 69.0,
            "upper": 152.80171679883915,
            "lower": 16.170575706533377
        },
        {
            "date": "2022-03-22",
            "cases": 62.0,
            "upper": 140.74413644019995,
            "lower": 12.799463310612307
        },
        {
            "date": "2022-03-23",
            "cases": 55.0,
            "upper": 127.3567492688558,
            "lower": 10.179421121640239
        },
        {
            "date": "2022-03-24",
            "cases": 50.0,
            "upper": 117.52518806217282,
            "lower": 7.640758811515159
        },
        {
            "date": "2022-03-25",
            "cases": 44.0,
            "upper": 107.59951917078787,
            "lower": 5.1998357357854985
        },
        {
            "date": "2022-03-26",
            "cases": 40.0,
            "upper": 100.08394467720375,
            "lower": 3.44660802372438
        },
        {
            "date": "2022-03-27",
            "cases": 36.0,
            "upper": 91.22581352871188,
            "lower": 1.7740622721770158
        },
        {
            "date": "2022-03-28",
            "cases": 32.0,
            "upper": 83.54329021495067,
            "lower": 0.7124854603860591
        },
        {
            "date": "2022-03-29",
            "cases": 29.0,
            "upper": 77.06688568561933,
            "lower": 0
        },
        {
            "date": "2022-03-30",
            "cases": 26.0,
            "upper": 70.51136328441436,
            "lower": 0
        },
        {
            "date": "2022-03-31",
            "cases": 23.0,
            "upper": 65.20053668938769,
            "lower": 0
        },
        {
            "date": "2022-04-01",
            "cases": 21.0,
            "upper": 59.82057887835976,
            "lower": 0
        },
        {
            "date": "2022-04-02",
            "cases": 18.0,
            "upper": 55.73301278052525,
            "lower": 0
        },
        {
            "date": "2022-04-03",
            "cases": 16.0,
            "upper": 51.59315505688107,
            "lower": 0
        },
        {
            "date": "2022-04-04",
            "cases": 15.0,
            "upper": 47.392648625356486,
            "lower": 0
        },
        {
            "date": "2022-04-05",
            "cases": 13.0,
            "upper": 44.55339197627562,
            "lower": 0
        },
        {
            "date": "2022-04-06",
            "cases": 12.0,
            "upper": 41.6783746344279,
            "lower": 0
        },
        {
            "date": "2022-04-07",
            "cases": 11.0,
            "upper": 37.28751453961394,
            "lower": 0
        },
        {
            "date": "2022-04-08",
            "cases": 9.0,
            "upper": 35.799759585393936,
            "lower": 0
        },
        {
            "date": "2022-04-09",
            "cases": 8.0,
            "upper": 32.7817742750964,
            "lower": 0
        },
        {
            "date": "2022-04-10",
            "cases": 8.0,
            "upper": 31.248883071815104,
            "lower": 0
        },
        {
            "date": "2022-04-11",
            "cases": 7.0,
            "upper": 28.12688691053065,
            "lower": 0
        },
        {
            "date": "2022-04-12",
            "cases": 6.0,
            "upper": 26.533442842809666,
            "lower": 0
        },
        {
            "date": "2022-04-13",
            "cases": 5.0,
            "upper": 24.91471214673331,
            "lower": 0
        },
        {
            "date": "2022-04-14",
            "cases": 5.0,
            "upper": 23.26715747203144,
            "lower": 0
        },
        {
            "date": "2022-04-15",
            "cases": 4.0,
            "upper": 21.5863307063223,
            "lower": 0
        },
        {
            "date": "2022-04-16",
            "cases": 4.0,
            "upper": 19.866506390262625,
            "lower": 0
        },
        {
            "date": "2022-04-17",
            "cases": 3.0,
            "upper": 18.100100322581582,
            "lower": 0
        },
        {
            "date": "2022-04-18",
            "cases": 3.0,
            "upper": 18.100100322581582,
            "lower": 0
        },
        {
            "date": "2022-04-19",
            "cases": 3.0,
            "upper": 16.27669598813781,
            "lower": 0
        },
        {
            "date": "2022-04-20",
            "cases": 2.0,
            "upper": 16.27669598813781,
            "lower": 0
        },
        {
            "date": "2022-04-21",
            "cases": 2.0,
            "upper": 14.381297015543204,
            "lower": 0.0
        },
        {
            "date": "2022-04-22",
            "cases": 2.0,
            "upper": 14.381297015543204,
            "lower": 0.0
        },
        {
            "date": "2022-04-23",
            "cases": 2.0,
            "upper": 12.390887137548201,
            "lower": 0.0
        },
        {
            "date": "2022-04-24",
            "cases": 1.0,
            "upper": 12.390887137548201,
            "lower": 0.0
        },
        {
            "date": "2022-04-25",
            "cases": 1.0,
            "upper": 10.266721421404833,
            "lower": 0.0
        },
        {
            "date": "2022-04-26",
            "cases": 1.0,
            "upper": 10.266721421404833,
            "lower": 0.0
        },
        {
            "date": "2022-04-27",
            "cases": 1.0,
            "upper": 10.266721421404833,
            "lower": 0.0
        },
        {
            "date": "2022-04-28",
            "cases": 1.0,
            "upper": 10.266721421404833,
            "lower": 0.0
        },
        {
            "date": "2022-04-29",
            "cases": 1.0,
            "upper": 10.266721421404833,
            "lower": 0.0
        },
        {
            "date": "2022-04-30",
            "cases": 1.0,
            "upper": 7.9332531951313126,
            "lower": 0.0
        },
        {
            "date": "2022-05-01",
            "cases": 1.0,
            "upper": 7.9332531951313126,
            "lower": 0.0
        }
    ],
    "SHOT_NOISE_FACTOR": 4.195443568774101,
    "R_eff_others": 1.5207640912378286,
    "R_eff_concern": 1.9357109687270408,
    "u_R_eff_others": 0.09311075221424381,
    "u_R_eff_concern": 0.10939032329970388,
    "u_R_eff": 0.11942972615672232,
    "today": "2021-12-30",
    "new_concern": 3009.172280824236,
    "cov_concern": [
        [
            21488.88087116737,
            14.831900774249931
        ],
        [
            14.831900774249931,
            0.011966242831613735
        ]
    ],
    "new_others": 4553.453024873108,
    "cov_others": [
        [
            61550.423147000125,
            21.689152707807278
        ],
        [
            21.689152707807278,
            0.008669612177902295
        ]
    ],
    "initial_cumulative_others": 64716,
    "initial_cumulative_concern": 74179,
    "R_eff_hunter": 0.8522194596162334,
    "u_R_eff_hunter": 0.10640405665986385,
    "new_hunter": 510.2337708655725,
    "cov_hunter": [
        [
            4546.828655460695,
            6.304599053245047
        ],
        [
            6.304599053245047,
            0.01132182327367551
        ]
    ],
    "initial_cumulative_hunter": 12856,
    "R_eff_wnsw": 1.9417930550873133,
    "u_R_eff_wnsw": 0.2968313004080939,
    "new_wnsw": 102.70665229987291,
    "cov_wnsw": [
        [
            196.40585628609156,
            3.6002140271184184
        ],
        [
            3.6002140271184184,
            0.08810882090196015
        ]
    ],
    "initial_cumulative_wnsw": 3012,
    "R_eff_illawarra": 2.079692539670241,
    "u_R_eff_illawarra": 0.26131911279171716,
    "new_illawarra": 220.15232832094594,
    "cov_illawarra": [
        [
            569.2789760492132,
            5.618293801011055
        ],
        [
            5.618293801011055,
            0.06828767871025014
        ]
    ],
    "initial_cumulative_illawarra": 4208,
    "R_eff_sydney": 1.8479776687382472,
    "u_R_eff_sydney": 0.11166517748301752,
    "new_sydney": 6407.231716193007,
    "cov_sydney": [
        [
            109172.27883337838,
            34.96651674982992
        ],
        [
            34.96651674982992,
            0.012469111862313809
        ]
    ],
    "initial_cumulative_sydney": 114137,
    "R_eff_not_sydney": 1.1342164702943367,
    "u_R_eff_not_sydney": 0.09263037708895139,
    "new_not_sydney": 1180.7578607681112,
    "cov_not_sydney": [
        [
            9380.212945303907,
            8.053296151347457
        ],
        [
            8.053296151347457,
            0.008580386759641317
        ]
    ],
    "initial_cumulative_not_sydney": 24758
}